<?xml version="1.0" encoding="utf-8"?>
<odoo>

    <data>
    
        <record id="mail_activity_type_view_form_inherit_department" model="ir.ui.view">
            <field name="name">mail.activity.type.view.form.inherit</field>
            <field name="model">mail.activity.type</field>
            <field name="inherit_id" ref="mail.mail_activity_type_view_form"/>
            <field name="arch" type="xml">
                <field name="summary" position="after">
                    <field name="job_id" />
                </field>
            </field>
        </record>
    
    </data>

</odoo>
